MANIFEST.in
README.rst
pyproject.toml
setup.cfg
src/bibliography/__init__.py
src/bibliography/__main__.py
src/bibliography/meta.py
src/bibliography/meta.sh
src/bibliography.egg-info/PKG-INFO
src/bibliography.egg-info/SOURCES.txt
src/bibliography.egg-info/dependency_links.txt
src/bibliography.egg-info/entry_points.txt
src/bibliography.egg-info/top_level.txt
src/bibliography/data/__init__.py
src/bibliography/data/quote.txt